loman/__init__.py
loman/compat.py
loman/computeengine.py
loman/consts.py
loman/exception.py
loman/graph_utils.py
loman/nodekey.py
loman/util.py
loman/visualization.py
loman/serialization/__init__.py
loman/serialization/default.py
loman/serialization/transformer.py
loman-0.5.3.dist-info/licenses/LICENSE
loman-0.5.3.dist-info/METADATA
loman-0.5.3.dist-info/WHEEL
loman-0.5.3.dist-info/top_level.txt
loman-0.5.3.dist-info/RECORD
