Metadata-Version: 2.4
Name: loman
Version: 0.5.3
Summary: Loman tracks state of computations, and the dependencies between them, allowing full and partial recalculations.
Author-email: Ed Parcell <edparcell@gmail.com>
License-Expression: BSD-3-Clause
Project-URL: Homepage, https://github.com/janusassetallocation/loman
Classifier: Programming Language :: Python :: 3
Classifier: Operating System :: OS Independent
Classifier: Development Status :: 4 - Beta
Classifier: Intended Audience :: Developers
Classifier: Topic :: Software Development :: Libraries
Requires-Python: >=3.9
License-File: LICENSE
Requires-Dist: decorator
Requires-Dist: matplotlib
Requires-Dist: pydotplus
Requires-Dist: dill>=0.2.5
Requires-Dist: networkx>=2.0
Requires-Dist: pandas>=0.19.2
Provides-Extra: test
Requires-Dist: attrs; extra == "test"
Requires-Dist: pytest; extra == "test"
Dynamic: license-file
